{
  "propertyKeys": [
    {"name": "name", "dataType": "String", "cardinality": "SINGLE"},
    {"name": "id", "dataType": "String", "cardinality": "SINGLE"},
    {"name": "code", "dataType": "String", "cardinality": "SINGLE"},
    {"name": "observation", "dataType": "String", "cardinality": "SINGLE"},
    {"name": "enable", "dataType": "Boolean", "cardinality": "SINGLE"},
    {"name": "creationDate", "dataType": "Date", "cardinality": "SINGLE"},
    {"name": "description", "dataType": "String", "cardinality": "SINGLE"},
    {"name": "expirationDate", "dataType": "Date", "cardinality": "SINGLE"}
  ],
  "vertexLabels": [
    {"name": "organization"},
    {"name": "unitOrganization"},
    {"name": "group"},
    {"name": "user"},
    {"name": "accessGroup"},
    {"name": "rule"},
    {"name": "accessRule"}
  ],
  "edgeLabels": [
    {"name": "has", "multiplicity": "MULTI"},
    {"name": "provide", "multiplicity": "MULTI"},
    {"name": "own", "multiplicity": "MULTI"},
    {"name": "add", "multiplicity": "MULTI"},
    {"name": "remove", "multiplicity": "MULTI"},
    {"name": "associated", "multiplicity": "MULTI"},
    {"name": "inherit", "multiplicity": "MULTI"}
  ],
  "vertexIndexes": [
    {"name": "vByOrganizationCode",
      "propertyKeys": ["code"],
      "composite": true,
      "unique": true,
      "indexOnly": "organization"},
    {"name": "vByUnitOrganizationCode",
      "propertyKeys": ["code"],
      "composite": true,
      "unique": true,
      "indexOnly": "unitOrganization"},
    {"name": "vByGroupCode",
      "propertyKeys": ["code"],
      "composite": true,
      "unique": true,
      "indexOnly": "group"},
    {"name": "vByUserCode",
      "propertyKeys": ["code"],
      "composite": true,
      "unique": true,
      "indexOnly": "user"},
    {"name": "vByUserId",
      "propertyKeys": ["id"],
      "composite": true,
      "unique": true,
      "indexOnly": "user"},
    {"name": "vByRuleId",
      "propertyKeys": ["id"],
      "composite": true,
      "unique": true,
      "indexOnly": "rule"},
    {"name": "accessRule",
      "propertyKeys": ["enable"],
      "composite": true,
      "unique": true,
      "indexOnly": "rule"},
    {"name": "vByAccessGroupId",
      "propertyKeys": ["id"],
      "composite": true,
      "unique": true,
      "indexOnly": "accessGroup"},
    {"name": "vByAccessGroupEnable",
      "propertyKeys": ["enable"],
      "composite": true,
      "unique": true,
      "indexOnly": "accessGroup"},
    {"name": "vByAssociationExpirationDate",
      "propertyKeys": ["expirationDate"],
      "composite": true,
      "unique": true,
      "indexOnly": "associtation"}
  ],
  "edgeIndexes": [
    {"name": "eByIdAdd",
      "propertyKeys": ["id"],
      "composite": true,
      "unique": false,
      "indexOnly": "add"},
    {"name": "eByIdRemove",
      "propertyKeys": ["id"],
      "composite": true,
      "unique": false,
      "indexOnly": "remove"}
  ],
  "vertexCentricIndexes":[
    {"name": "vcByUser",
      "propertyKeys": ["id", "code"],
      "edge": "associated",
      "direction": "BOTH",
      "order": "incr"}
  ]
}